.dockerignore
CHANGES.rst
CHECKS
Dockerfile
LICENSE
MANIFEST.in
Procfile
README.rst
bootstrap.py
buildout.cfg
checkouts.cfg
codep
deployment.cfg
development.ini
docker-compose-dev.yml
docker-compose.override.yml.templ
docker-compose.yml
gulpfile.js
heroku.cfg
jenkins.cfg
nginx-app-dev.conf
nginx-app-prod.conf
nginx.conf
package.json
production-heroku.ini
production.ini
requirements.txt
run.sh
setup.cfg
setup.py
sources.cfg
start.bash
start_all.bash
start_system.bash
versions.cfg
etc/varnish.vcl
etc/zeo.conf
etc/zodb.conf
html/robots.txt
novaideo/__init__.py
novaideo/cache.py
novaideo/catalog.py
novaideo/contextual_help_messages.py
novaideo/core.py
novaideo/core_schema.py
novaideo/dateindex.py
novaideo/emojis.py
novaideo/event.py
novaideo/fr_lexicon.py
novaideo/fr_stopdict.py
novaideo/guide_tour.py
novaideo/layout.py
novaideo/mail.py
novaideo/role.py
novaideo/steps.py
novaideo/subscribers.py
novaideo/testing.py
novaideo.egg-info/PKG-INFO
novaideo.egg-info/SOURCES.txt
novaideo.egg-info/dependency_links.txt
novaideo.egg-info/entry_points.txt
novaideo.egg-info/not-zip-safe
novaideo.egg-info/requires.txt
novaideo.egg-info/top_level.txt
novaideo/adapters/__init__.py
novaideo/adapters/report_adapter.py
novaideo/content/__init__.py
novaideo/content/alert.py
novaideo/content/amendment.py
novaideo/content/ballot.py
novaideo/content/bot.py
novaideo/content/candidacy.py
novaideo/content/challenge.py
novaideo/content/comment.py
novaideo/content/correction.py
novaideo/content/correlation.py
novaideo/content/file.py
novaideo/content/idea.py
novaideo/content/interface.py
novaideo/content/invitation.py
novaideo/content/keyword.py
novaideo/content/newsletter.py
novaideo/content/novaideo_application.py
novaideo/content/organization.py
novaideo/content/person.py
novaideo/content/proposal.py
novaideo/content/question.py
novaideo/content/report.py
novaideo/content/resources.py
novaideo/content/site_configuration.py
novaideo/content/smart_folder.py
novaideo/content/token.py
novaideo/content/web_advertising.py
novaideo/content/working_group.py
novaideo/content/workspace.py
novaideo/content/processes/__init__.py
novaideo/content/processes/admin_process/__init__.py
