Metadata-Version: 1.1
Name: novaideo
Version: 1.3
Summary: Nova-Ideo is a participatory innovation tool, the merger of the box ideas and collaborative portal.
Home-page: https://nova-ideo.com
Author: Amen Souissi
Author-email: amensouissi@ecreall.com
License: AGPLv3+
Keywords: web pyramid substanced
Platform: UNKNOWN
Classifier: Programming Language :: Python
Classifier: Programming Language :: Python :: 3.4
Classifier: Framework :: Pyramid
Classifier: Topic :: Internet :: WWW/HTTP
Classifier: Topic :: Internet :: WWW/HTTP :: WSGI :: Application
Classifier: License :: OSI Approved :: GNU Affero General Public License v3 or later (AGPLv3+)
